email_auth/__init__.py
email_auth/admin.py
email_auth/app_settings.py
email_auth/apps.py
email_auth/authentication.py
email_auth/conftest.py
email_auth/models.py
email_auth/interfaces/__init__.py
email_auth/interfaces/rest/__init__.py
email_auth/interfaces/rest/apps.py
email_auth/interfaces/rest/openapi.yml
email_auth/interfaces/rest/serializers.py
email_auth/interfaces/rest/urls.py
email_auth/interfaces/rest/views.py
email_auth/interfaces/rest/templates/email_auth/emails/reset-password.txt
email_auth/interfaces/rest/templates/email_auth/emails/verify-email.txt
email_auth/interfaces/rest/test/__init__.py
email_auth/interfaces/rest/test/serializers/__init__.py
email_auth/interfaces/rest/test/serializers/test_email_verification_request_serializer.py
email_auth/interfaces/rest/test/serializers/test_email_verification_serializer.py
email_auth/interfaces/rest/test/serializers/test_password_reset_request_serializer.py
email_auth/interfaces/rest/test/serializers/test_password_reset_serializer.py
email_auth/interfaces/rest/test/views/__init__.py
email_auth/interfaces/rest/test/views/test_email_verification_request_view.py
email_auth/interfaces/rest/test/views/test_email_verification_view.py
email_auth/interfaces/rest/test/views/test_password_reset_request_view.py
email_auth/interfaces/rest/test/views/test_password_reset_view.py
email_auth/migrations/0001_initial.py
email_auth/migrations/0002_emailverification.py
email_auth/migrations/0003_rm_emailaddress_normalizedaddress.py
email_auth/migrations/0004_passwordreset.py
email_auth/migrations/__init__.py
email_auth/templates/email_auth/emails/already-verified.txt
email_auth/templates/email_auth/emails/duplicate-email.txt
email_auth/templates/email_auth/emails/reset-password.txt
email_auth/templates/email_auth/emails/unregistered-email.txt
email_auth/templates/email_auth/emails/verify-email.txt
email_auth/test/__init__.py
email_auth/test/test_app_settings.py
email_auth/test/test_utils.py
django_simple_email_auth-0.4.0.dist-info/LICENSE
django_simple_email_auth-0.4.0.dist-info/METADATA
django_simple_email_auth-0.4.0.dist-info/WHEEL
django_simple_email_auth-0.4.0.dist-info/top_level.txt
django_simple_email_auth-0.4.0.dist-info/RECORD
