Metadata-Version: 2.1
Name: django-simple-email-auth
Version: 0.4.0
Summary: Django app for email based authentication and registration.
Home-page: https://github.com/cdriehuys/django-simple-email-auth
Author: Chathan Driehuys
Author-email: chathan@driehuys.com
License: MIT
Platform: UNKNOWN
Classifier: Development Status :: 3 - Alpha
Classifier: Framework :: Django
Classifier: Framework :: Django :: 2.1
Classifier: Framework :: Django :: 2.2
Classifier: Intended Audience :: Developers
Classifier: License :: OSI Approved :: MIT License
Classifier: Natural Language :: English
Classifier: Programming Language :: Python
Classifier: Programming Language :: Python :: 3
Classifier: Programming Language :: Python :: 3.6
Classifier: Programming Language :: Python :: 3.7
Requires-Dist: Django (>=2.1)
Requires-Dist: django-email-utils (>=1.0)
Provides-Extra: rest
Requires-Dist: djangorestframework ; extra == 'rest'
